pamai/__init__.py
pamai/version.py
pamai/agents/__init__.py
pamai/agents/base.py
pamai/agents/denet.py
pamai/config/__init__.py
pamai/config/hparams.py
pamai/datasets/__init__.py
pamai/datasets/raw_audio.py
pamai/datasets/raw_audio_dataset.py
pamai/graphs/__init__.py
pamai/graphs/weights_initializer.py
pamai/graphs/losses/__init__.py
pamai/graphs/losses/example.py
pamai/graphs/losses/utils.py
pamai/graphs/models/__init__.py
pamai/graphs/models/denet.py
pamai/graphs/models/sincnet.py
pamai/graphs/models/custom_layers/MLP_sincnet.py
pamai/graphs/models/custom_layers/__init__.py
pamai/graphs/models/custom_layers/de_layer.py
pamai/graphs/models/custom_layers/layer_norm.py
pamai/graphs/models/custom_layers/sinc_conv.py
pamai/graphs/models/custom_layers/time_distributed.py
pamai/utils/__init__.py
pamai/utils/metrics.py
pamai/utils/misc.py
pamai/utils/process_database.py
pamai/utils/signal_processing.py
pamai/utils/train_utils.py
pamai-1.0.5.dist-info/LICENSE.txt
pamai-1.0.5.dist-info/METADATA
pamai-1.0.5.dist-info/WHEEL
pamai-1.0.5.dist-info/top_level.txt
pamai-1.0.5.dist-info/RECORD
