Metadata-Version: 2.1
Name: pamai
Version: 1.0.5
Summary: Package for PAMAI written by Arthur Zucker and Chris Rauch.
Home-page: https://github.com/ArthurZucker/PAMAI
Download-URL: https://github.com/ArthurZucker/PAMAI/archive/refs/tags/v1.0.5.tar.gz
Author: Chris Rauch
Author-email: chrisrauch193@gmail.com
License: MIT
Keywords: pamai,ai,audio,denet,arthur,zucker
Classifier: Development Status :: 5 - Production/Stable
Classifier: Intended Audience :: Developers
Classifier: Topic :: Software Development :: Build Tools
Classifier: License :: OSI Approved :: MIT License
Classifier: Programming Language :: Python :: 3.8
Requires-Python: ~=3.8
License-File: LICENSE.txt
Requires-Dist: PyAudio (==0.2.13)
Requires-Dist: pybind11 (==2.10.4)
Requires-Dist: Cython (==0.29.34)
Requires-Dist: numpy (==1.23.5)
Requires-Dist: certifi (==2022.12.7)
Requires-Dist: versioneer (==0.28)
Requires-Dist: dcase-util (==0.2.20)
Requires-Dist: easydict (==1.10)
Requires-Dist: matplotlib (==3.7.1)
Requires-Dist: pythran (==0.12.1)
Requires-Dist: pandas (==2.0.0)
Requires-Dist: pypandoc (==1.11)
Requires-Dist: runx (==0.0.11)
Requires-Dist: scikit-learn (==1.2.2)
Requires-Dist: scipy (==1.10.1)
Requires-Dist: simple-parsing (==0.1.2)
Requires-Dist: torch (==2.0.0)
Requires-Dist: torchaudio (==2.0.1)
Requires-Dist: tqdm (==4.65.0)
Requires-Dist: wandb (==0.15.0)
